brevis/__init__.py
brevis-0.6.0.dist-info/LICENSE
brevis-0.6.0.dist-info/METADATA
brevis-0.6.0.dist-info/WHEEL
brevis-0.6.0.dist-info/top_level.txt
brevis-0.6.0.dist-info/RECORD
