Metadata-Version: 2.1
Name: brevis
Version: 0.6.0
Summary: Python client for the Brevis URL shortener API
Home-page: http://github.com/admiralobvious/brevis-python-client
Author: Alexandre Ferland
Author-email: aferlandqc@gmail.com
License: MIT
Platform: any
Classifier: Intended Audience :: Developers
Classifier: License :: OSI Approved :: MIT License
Classifier: Operating System :: OS Independent
Classifier: Programming Language :: Python :: 3.5
Classifier: Programming Language :: Python :: 3.6
Classifier: Programming Language :: Python :: 3.7
Classifier: Topic :: Software Development :: Libraries :: Python Modules
Requires-Dist: requests (>=2.22)
